odoo/addons/delivery_postlogistics_dangerous_goods/README.rst
odoo/addons/delivery_postlogistics_dangerous_goods/__init__.py
odoo/addons/delivery_postlogistics_dangerous_goods/__manifest__.py
odoo/addons/delivery_postlogistics_dangerous_goods/i18n/delivery_postlogistics_dangerous_goods.pot
odoo/addons/delivery_postlogistics_dangerous_goods/i18n/es.po
odoo/addons/delivery_postlogistics_dangerous_goods/i18n/it.po
odoo/addons/delivery_postlogistics_dangerous_goods/models/__init__.py
odoo/addons/delivery_postlogistics_dangerous_goods/models/stock_picking.py
odoo/addons/delivery_postlogistics_dangerous_goods/postlogistics/__init__.py
odoo/addons/delivery_postlogistics_dangerous_goods/postlogistics/web_service.py
odoo/addons/delivery_postlogistics_dangerous_goods/readme/CONTRIBUTORS.rst
odoo/addons/delivery_postlogistics_dangerous_goods/readme/DESCRIPTION.rst
odoo/addons/delivery_postlogistics_dangerous_goods/static/description/icon.png
odoo/addons/delivery_postlogistics_dangerous_goods/static/description/index.html
odoo/addons/delivery_postlogistics_dangerous_goods/tests/__init__.py
odoo/addons/delivery_postlogistics_dangerous_goods/tests/test_postlogistics_dangerous_goods.py
odoo14_addon_delivery_postlogistics_dangerous_goods-14.0.1.0.1.dev10.dist-info/METADATA
odoo14_addon_delivery_postlogistics_dangerous_goods-14.0.1.0.1.dev10.dist-info/WHEEL
odoo14_addon_delivery_postlogistics_dangerous_goods-14.0.1.0.1.dev10.dist-info/top_level.txt
odoo14_addon_delivery_postlogistics_dangerous_goods-14.0.1.0.1.dev10.dist-info/RECORD
