Metadata-Version: 2.1
Name: odoo14-addon-delivery_postlogistics_dangerous_goods
Version: 14.0.1.0.1.dev10
Summary: Declare dangerous goods when generating postlogistics labels
Home-page: https://github.com/OCA/delivery-carrier
Author: Camptocamp,Odoo Community Association (OCA)
Author-email: support@odoo-community.org
License: AGPL-3
Classifier: Programming Language :: Python
Classifier: Framework :: Odoo
Classifier: Framework :: Odoo :: 14.0
Classifier: License :: OSI Approved :: GNU Affero General Public License v3
Requires-Python: >=3.6
Requires-Dist: odoo14-addon-delivery-postlogistics
Requires-Dist: odoo14-addon-l10n-eu-product-adr-dangerous-goods
Requires-Dist: odoo<14.1dev,>=14.0a
